{
  "artists": {
    "artist": [
      {
        "name": "The Weeknd",
        "playcount": "258665615",
        "listeners": "2427690",
        "mbid": "c8b03190-306c-4120-bb0b-6f2ebfc06ea9",
        "url": "https://www.last.fm/music/The+Weeknd",
        "streamable": "0",
        "image": [
          {
            "#text": "https://lastfm.freetls.fastly.net/i/u/34s/2a96cbd8b46e442fc41c2b86b821562f.png",
            "size": "small"
          },
          {
            "#text": "https://lastfm.freetls.fastly.net/i/u/64s/2a96cbd8b46e442fc41c2b86b821562f.png",
            "size": "medium"
          },
          {
            "#text": "https://lastfm.freetls.fastly.net/i/u/174s/2a96cbd8b46e442fc41c2b86b821562f.png",
            "size": "large"
          },
          {
            "#text": "https://lastfm.freetls.fastly.net/i/u/300x300/2a96cbd8b46e442fc41c2b86b821562f.png",
            "size": "extralarge"
          },
          {
            "#text": "https://lastfm.freetls.fastly.net/i/u/300x300/2a96cbd8b46e442fc41c2b86b821562f.png",
            "size": "mega"
          }
        ]
      },
      {
        "name": "Kanye West",
        "playcount": "525328018",
        "listeners": "5331212",
        "mbid": "164f0d73-1234-4e2c-8743-d77bf2191051",
        "url": "https://www.last.fm/music/Kanye+West",
        "streamable": "0",
        "image": [
          {
            "#text": "https://lastfm.freetls.fastly.net/i/u/34s/2a96cbd8b46e442fc41c2b86b821562f.png",
            "size": "small"
          },
          {
            "#text": "https://lastfm.freetls.fastly.net/i/u/64s/2a96cbd8b46e442fc41c2b86b821562f.png",
            "size": "medium"
          },
          {
            "#text": "https://lastfm.freetls.fastly.net/i/u/174s/2a96cbd8b46e442fc41c2b86b821562f.png",
            "size": "large"
          },
          {
            "#text": "https://lastfm.freetls.fastly.net/i/u/300x300/2a96cbd8b46e442fc41c2b86b821562f.png",
            "size": "extralarge"
          },
          {
            "#text": "https://lastfm.freetls.fastly.net/i/u/300x300/2a96cbd8b46e442fc41c2b86b821562f.png",
            "size": "mega"
          }
        ]
      },
      {
        "name": "Doja Cat",
        "playcount": "120556584",
        "listeners": "1289160",
        "mbid": "5df62a88-cac9-490a-b62c-c7c88f4020f4",
        "url": "https://www.last.fm/music/Doja+Cat",
        "streamable": "0",
        "image": [
          {
            "#text": "https://lastfm.freetls.fastly.net/i/u/34s/2a96cbd8b46e442fc41c2b86b821562f.png",
            "size": "small"
          },
          {
            "#text": "https://lastfm.freetls.fastly.net/i/u/64s/2a96cbd8b46e442fc41c2b86b821562f.png",
            "size": "medium"
          },
          {
            "#text": "https://lastfm.freetls.fastly.net/i/u/174s/2a96cbd8b46e442fc41c2b86b821562f.png",
            "size": "large"
          },
          {
            "#text": "https://lastfm.freetls.fastly.net/i/u/300x300/2a96cbd8b46e442fc41c2b86b821562f.png",
            "size": "extralarge"
          },
          {
            "#text": "https://lastfm.freetls.fastly.net/i/u/300x300/2a96cbd8b46e442fc41c2b86b821562f.png",
            "size": "mega"
          }
        ]
      },
      {
        "name": "Taylor Swift",
        "playcount": "662953750",
        "listeners": "3181109",
        "mbid": "20244d07-534f-4eff-b4d4-930878889970",
        "url": "https://www.last.fm/music/Taylor+Swift",
        "streamable": "0",
        "image": [
          {
            "#text": "https://lastfm.freetls.fastly.net/i/u/34s/2a96cbd8b46e442fc41c2b86b821562f.png",
            "size": "small"
          },
          {
            "#text": "https://lastfm.freetls.fastly.net/i/u/64s/2a96cbd8b46e442fc41c2b86b821562f.png",
            "size": "medium"
          },
          {
            "#text": "https://lastfm.freetls.fastly.net/i/u/174s/2a96cbd8b46e442fc41c2b86b821562f.png",
            "size": "large"
          },
          {
            "#text": "https://lastfm.freetls.fastly.net/i/u/300x300/2a96cbd8b46e442fc41c2b86b821562f.png",
            "size": "extralarge"
          },
          {
            "#text": "https://lastfm.freetls.fastly.net/i/u/300x300/2a96cbd8b46e442fc41c2b86b821562f.png",
            "size": "mega"
          }
        ]
      },
      {
        "name": "Billie Eilish",
        "playcount": "164348703",
        "listeners": "1574508",
        "mbid": "",
        "url": "https://www.last.fm/music/Billie+Eilish",
        "streamable": "0",
        "image": [
          {
            "#text": "https://lastfm.freetls.fastly.net/i/u/34s/2a96cbd8b46e442fc41c2b86b821562f.png",
            "size": "small"
          },
          {
            "#text": "https://lastfm.freetls.fastly.net/i/u/64s/2a96cbd8b46e442fc41c2b86b821562f.png",
            "size": "medium"
          },
          {
            "#text": "https://lastfm.freetls.fastly.net/i/u/174s/2a96cbd8b46e442fc41c2b86b821562f.png",
            "size": "large"
          },
          {
            "#text": "https://lastfm.freetls.fastly.net/i/u/300x300/2a96cbd8b46e442fc41c2b86b821562f.png",
            "size": "extralarge"
          },
          {
            "#text": "https://lastfm.freetls.fastly.net/i/u/300x300/2a96cbd8b46e442fc41c2b86b821562f.png",
            "size": "mega"
          }
        ]
      },
      {
        "name": "Drake",
        "playcount": "277923298",
        "listeners": "4263574",
        "mbid": "b49b81cc-d5b7-4bdd-aadb-385df8de69a6",
        "url": "https://www.last.fm/music/Drake",
        "streamable": "0",
        "image": [
          {
            "#text": "https://lastfm.freetls.fastly.net/i/u/34s/2a96cbd8b46e442fc41c2b86b821562f.png",
            "size": "small"
          },
          {
            "#text": "https://lastfm.freetls.fastly.net/i/u/64s/2a96cbd8b46e442fc41c2b86b821562f.png",
            "size": "medium"
          },
          {
            "#text": "https://lastfm.freetls.fastly.net/i/u/174s/2a96cbd8b46e442fc41c2b86b821562f.png",
            "size": "large"
          },
          {
            "#text": "https://lastfm.freetls.fastly.net/i/u/300x300/2a96cbd8b46e442fc41c2b86b821562f.png",
            "size": "extralarge"
          },
          {
            "#text": "https://lastfm.freetls.fastly.net/i/u/300x300/2a96cbd8b46e442fc41c2b86b821562f.png",
            "size": "mega"
          }
        ]
      },
      {
        "name": "Tyler, the Creator",
        "playcount": "204202656",
        "listeners": "1633894",
        "mbid": "f6beac20-5dfe-4d1f-ae02-0b0a740aafd6",
        "url": "https://www.last.fm/music/Tyler,+the+Creator",
        "streamable": "0",
        "image": [
          {
            "#text": "https://lastfm.freetls.fastly.net/i/u/34s/2a96cbd8b46e442fc41c2b86b821562f.png",
            "size": "small"
          },
          {
            "#text": "https://lastfm.freetls.fastly.net/i/u/64s/2a96cbd8b46e442fc41c2b86b821562f.png",
            "size": "medium"
          },
          {
            "#text": "https://lastfm.freetls.fastly.net/i/u/174s/2a96cbd8b46e442fc41c2b86b821562f.png",
            "size": "large"
          },
          {
            "#text": "https://lastfm.freetls.fastly.net/i/u/300x300/2a96cbd8b46e442fc41c2b86b821562f.png",
            "size": "extralarge"
          },
          {
            "#text": "https://lastfm.freetls.fastly.net/i/u/300x300/2a96cbd8b46e442fc41c2b86b821562f.png",
            "size": "mega"
          }
        ]
      },
      {
        "name": "Kendrick Lamar",
        "playcount": "199676415",
        "listeners": "2286370",
        "mbid": "381086ea-f511-4aba-bdf9-71c753dc5077",
        "url": "https://www.last.fm/music/Kendrick+Lamar",
        "streamable": "0",
        "image": [
          {
            "#text": "https://lastfm.freetls.fastly.net/i/u/34s/2a96cbd8b46e442fc41c2b86b821562f.png",
            "size": "small"
          },
          {
            "#text": "https://lastfm.freetls.fastly.net/i/u/64s/2a96cbd8b46e442fc41c2b86b821562f.png",
            "size": "medium"
          },
          {
            "#text": "https://lastfm.freetls.fastly.net/i/u/174s/2a96cbd8b46e442fc41c2b86b821562f.png",
            "size": "large"
          },
          {
            "#text": "https://lastfm.freetls.fastly.net/i/u/300x300/2a96cbd8b46e442fc41c2b86b821562f.png",
            "size": "extralarge"
          },
          {
            "#text": "https://lastfm.freetls.fastly.net/i/u/300x300/2a96cbd8b46e442fc41c2b86b821562f.png",
            "size": "mega"
          }
        ]
      }
    ],
    "@attr": {
      "page": "1",
      "perPage": "8",
      "totalPages": "524225",
      "total": "4193796"
    }
  }
}
